tiktokcaptions/__init__.py
tiktokcaptions/captions.py
tiktokcaptions/segment_parser.py
tiktokcaptions/text_drawer.py
tiktokcaptions/assets/fonts/Montserrat-Bold.ttf
tiktokcaptions/assets/fonts/Montserrat-ExtraBold.ttf
tiktokcaptions-0.1.2.dist-info/METADATA
tiktokcaptions-0.1.2.dist-info/WHEEL
tiktokcaptions-0.1.2.dist-info/top_level.txt
tiktokcaptions-0.1.2.dist-info/RECORD
