Metadata-Version: 2.1
Name: tiktokcaptions
Version: 0.1.2
Summary: Add TikTok-style captions to videos
Home-page: https://github.com/0xIbra/tiktokcaptions
Author: 0xIbra
Author-email: ibragim.ai95@gmail.com
Classifier: Programming Language :: Python :: 3
Classifier: License :: OSI Approved :: MIT License
Classifier: Operating System :: OS Independent
Requires-Python: >=3.7
Requires-Dist: moviepy
Requires-Dist: numpy
Requires-Dist: Pillow
Requires-Dist: opencv-python
